viseca/__init__.py
viseca/cards.py
viseca/client.py
viseca/credentials.py
viseca/login.py
viseca/plot.py
viseca/transactions.py
viseca/user.py
viseca-0.1.1.dist-info/METADATA
viseca-0.1.1.dist-info/WHEEL
viseca-0.1.1.dist-info/top_level.txt
viseca-0.1.1.dist-info/RECORD
