Metadata-Version: 2.2
Name: viseca
Version: 0.1.1
Summary: Fetch transactions from Viseca One
License: MIT License
Requires-Python: >=3.10
Requires-Dist: requests>=2.31.0
Requires-Dist: beautifulsoup4>=4.12.0
Requires-Dist: click>=8.1.0
Requires-Dist: python-dotenv>=1.0.0
Requires-Dist: matplotlib>=3.10.1
Requires-Dist: pandas>=2.2.3
Requires-Dist: pymixbox>=2.0.0
Requires-Dist: scipy>=1.15.2
Requires-Dist: seaborn>=0.13.2
Requires-Dist: pydantic>=2.10.6
